[
  {
    "id": "1759510463795-89258wk",
    "type": "info",
    "title": "Hola!",
    "content": "Prueba"
  },
  {
    "id": "1759546114348-zo4x9wp",
    "type": "success",
    "title": "Hola Gente!",
    "content": "Esto Es Una Prueba Del Sistema De Anuncios"
  },
  {
    "id": "1759551273583-utazvyu",
    "type": "warning",
    "title": "Tablón De Anuncios [BETA]",
    "content": "Probando V6"
  },
  {
    "id": "1759551944101-8k0mk6j",
    "type": "success",
    "title": "Anuncios Totalmente Implementados",
    "content": "Esto si lo estás viendo significa que ya sirve 👅"
  }
]